hhru/__init__.py
hhru/__version__.py
hhru/auth/__init__.py
hhru/auth/providers/__init__.py
hhru/auth/providers/_direct_auth.py
hhru/auth/providers/abstract.py
hhru/auth/providers/anonymous.py
hhru/auth/type.py
hhru/backend/__init__.py
hhru/backend/abstract/__init__.py
hhru/backend/abstract/abstract.py
hhru/backend/api/__init__.py
hhru/backend/api/consts.py
hhru/backend/api/http_response.py
hhru/backend/api/provider.py
hhru/backend/protocol.py
hhru/backend/web/__init__.py
hhru/backend/web/consts.py
hhru/backend/web/provider.py
hhru/client.py
hhru/consts.py
hhru/dto/__init__.py
hhru/dto/vacancy.py
hhru/py.typed
hhru-0.1.3.dist-info/LICENSE
hhru-0.1.3.dist-info/METADATA
hhru-0.1.3.dist-info/WHEEL
hhru-0.1.3.dist-info/RECORD
